setup.py
lzhtools/Config.py
lzhtools/__init__.py
lzhtools/corrplot.py
lzhtools/dac.py
lzhtools/lfile.py
lzhtools/lzhmssql.py
lzhtools/mylog.py
lzhtools/pub_func.py
lzhtools/tongjimssql.py
lzhtools.egg-info/PKG-INFO
lzhtools.egg-info/SOURCES.txt
lzhtools.egg-info/dependency_links.txt
lzhtools.egg-info/top_level.txt