Metadata-Version: 1.1
Name: lzhtools
Version: 0.1.0
Summary: UNKNOWN
Home-page: http://www.ac3.cn
Author: lizenghai
Author-email: 860007600@qq.com
License: BSD
Keywords: China stock data,futures trade,Stock trade,backtesting
Platform: UNKNOWN
Classifier: Development Status :: 4 - Beta
Classifier: Programming Language :: Python :: 3.2
Classifier: Programming Language :: Python :: 3.3
Classifier: Programming Language :: Python :: 3.4
Classifier: Programming Language :: Python :: 3.5
Classifier: License :: OSI Approved :: BSD License
